coremltools/__init__.py
coremltools/libcoremlpython.so
coremltools/libmilstoragepython.so
coremltools/libmodelpackage.so
coremltools/version.py
coremltools/_deps/__init__.py
coremltools/_deps/kmeans1d/__init__.py
coremltools/_deps/kmeans1d/_core.cpython-313-darwin.so
coremltools/_deps/kmeans1d/core.py
coremltools/converters/__init__.py
coremltools/converters/_converters_entry.py
coremltools/converters/_profile_utils.py
coremltools/converters/libsvm/__init__.py
coremltools/converters/libsvm/_libsvm_converter.py
coremltools/converters/libsvm/_libsvm_util.py
coremltools/converters/mil/__init__.py
coremltools/converters/mil/_deployment_compatibility.py
coremltools/converters/mil/conftest.py
coremltools/converters/mil/converter.py
coremltools/converters/mil/debugging_utils.py
coremltools/converters/mil/input_types.py
coremltools/converters/mil/test_inputs_outputs_shape.py
coremltools/converters/mil/testing_reqs.py
coremltools/converters/mil/testing_utils.py
coremltools/converters/mil/backend/__init__.py
coremltools/converters/mil/backend/backend_helper.py
coremltools/converters/mil/backend/mil/__init__.py
coremltools/converters/mil/backend/mil/helper.py
coremltools/converters/mil/backend/mil/load.py
coremltools/converters/mil/backend/mil/test_helper.py
coremltools/converters/mil/backend/mil/test_load.py
coremltools/converters/mil/backend/mil/passes/__init__.py
coremltools/converters/mil/backend/mil/passes/adjust_io_to_supported_types.py
coremltools/converters/mil/backend/mil/passes/fuse_activation_silu.py
coremltools/converters/mil/backend/mil/passes/fuse_pow2_sqrt.py
coremltools/converters/mil/backend/mil/passes/insert_image_preprocessing_op.py
coremltools/converters/mil/backend/mil/passes/sanitize_name_strings.py
coremltools/converters/mil/backend/mil/passes/test_passes.py
coremltools/converters/mil/backend/nn/__init__.py
coremltools/converters/mil/backend/nn/load.py
coremltools/converters/mil/backend/nn/mil_to_nn_mapping_registry.py
coremltools-9.0.dist-info/licenses/LICENSE.txt
coremltools-9.0.dist-info/licenses/NOTICE.txt
coremltools-9.0.dist-info/METADATA
coremltools-9.0.dist-info/WHEEL
coremltools-9.0.dist-info/top_level.txt
coremltools-9.0.dist-info/RECORD
