Metadata-Version: 2.1
Name: coremltools
Version: 9.0
Summary: Community Tools for Core ML
Home-page: https://github.com/apple/coremltools
Author: Apple Inc.
Author-email: coremltools@apple.com
License: BSD
Classifier: Development Status :: 5 - Production/Stable
Classifier: Intended Audience :: Developers
Classifier: Operating System :: MacOS :: MacOS X
Classifier: Operating System :: POSIX :: Linux
Classifier: Programming Language :: Python :: 3.7
Classifier: Programming Language :: Python :: 3.8
Classifier: Programming Language :: Python :: 3.9
Classifier: Programming Language :: Python :: 3.10
Classifier: Programming Language :: Python :: 3.11
Classifier: Programming Language :: Python :: 3.12
Classifier: Programming Language :: Python :: 3.13
Classifier: Topic :: Scientific/Engineering
Classifier: Topic :: Software Development
License-File: LICENSE.txt
License-File: NOTICE.txt
Requires-Dist: numpy >=1.14.5
Requires-Dist: protobuf >=3.1.0
Requires-Dist: sympy
Requires-Dist: tqdm
Requires-Dist: packaging
Requires-Dist: attrs >=21.3.0
Requires-Dist: cattrs
Requires-Dist: pyaml
